bible_summary/__init__.py
bible_summary/summary.py
bible_summary/data/1-chronicles.json
bible_summary/data/1-corinthians.json
bible_summary/data/1-john.json
bible_summary/data/1-kings.json
bible_summary/data/1-peter.json
bible_summary/data/1-samuel.json
bible_summary/data/1-thessalonians.json
bible_summary/data/1-timothy.json
bible_summary/data/2-chronicles.json
bible_summary/data/2-corinthians.json
bible_summary/data/2-john.json
bible_summary/data/2-kings.json
bible_summary/data/2-peter.json
bible_summary/data/2-samuel.json
bible_summary/data/2-thessalonians.json
bible_summary/data/2-timothy.json
bible_summary/data/3-john.json
bible_summary/data/acts.json
bible_summary/data/amos.json
bible_summary/data/colossians.json
bible_summary/data/daniel.json
bible_summary/data/deuteronomy.json
bible_summary/data/ecclesiastes.json
bible_summary/data/ephesians.json
bible_summary/data/esther.json
bible_summary/data/exodus.json
bible_summary/data/ezekiel.json
bible_summary/data/ezra.json
bible_summary/data/galatians.json
bible_summary/data/genesis.json
bible_summary/data/habakkuk.json
bible_summary/data/haggai.json
bible_summary/data/hebrews.json
bible_summary/data/hosea.json
bible_summary/data/isaiah.json
bible_summary/data/james.json
bible_summary/data/jeremiah.json
bible_summary/data/job.json
bible_summary/data/joel.json
bible_summary/data/john.json
bible_summary/data/jonah.json
bible_summary/data/joshua.json
bible_summary/data/jude.json
bible_summary/data/judges.json
bible_summary/data/lamentations.json
bible_summary/data/leviticus.json
bible_summary/data/luke.json
bible_summary/data/malachi.json
bible_summary/data/mark.json
bible_summary/data/matthew.json
bible_summary/data/micah.json
bible_summary/data/nahum.json
bible_summary/data/nehemiah.json
bible_summary/data/numbers.json
bible_summary/data/obadiah.json
bible_summary/data/philemon.json
bible_summary/data/philippians.json
bible_summary/data/proverbs.json
bible_summary/data/psalms.json
bible_summary-0.1.4.dist-info/METADATA
bible_summary-0.1.4.dist-info/WHEEL
bible_summary-0.1.4.dist-info/entry_points.txt
bible_summary-0.1.4.dist-info/top_level.txt
bible_summary-0.1.4.dist-info/RECORD
