Metadata-Version: 2.1
Name: bible-summary
Version: 0.1.4
Summary: A package for summarizing Bible books
Home-page: https://rikim.me/docs/bible-summary/
Author: Riki Morohashi
Author-email: rikimorohashi@gmail.com
License: UNKNOWN
Platform: UNKNOWN
Classifier: Programming Language :: Python :: 3
Classifier: License :: OSI Approved :: MIT License
Classifier: Operating System :: OS Independent
